auxi/mpp/__init__.py
auxi/mpp/py.typed
auxi/mpp/core/__init__.py
auxi/mpp/core/_condensed_material_property_model.py
auxi/mpp/core/_dataset.py
auxi/mpp/core/_dataset.template.csv
auxi/mpp/core/_material_component_property_model.py
auxi/mpp/core/_material_model.py
auxi/mpp/core/_material_property_model.py
auxi/mpp/core/_material_type.py
auxi/mpp/core/_state_of_matter.py
auxi/mpp/core/py.typed
auxi/mpp/core/material_state/__init__.py
auxi/mpp/core/material_state/_material_state.py
auxi/mpp/core/material_state/_tpx_state.py
auxi/mpp/core/material_state/py.typed
auxi/mpp/gas/__init__.py
auxi/mpp/gas/_gas_property_model.py
auxi/mpp/gas/_gas_radiation_property_model.py
auxi/mpp/gas/Cp/__init__.py
auxi/mpp/gas/Cp/_aly_unary.py
auxi/mpp/gas/Cp/_aly_unary.yaml
auxi/mpp/gas/Cp/_model.py
auxi/mpp/gas/D/__init__.py
auxi/mpp/gas/D/_burgess_unary.py
auxi/mpp/gas/D/_burgess_unary.yaml
auxi/mpp/gas/D/_hellmann_binary.py
auxi/mpp/gas/D/_hellmann_binary.yaml
auxi/mpp/gas/D/_model.py
auxi/mpp/gas/Vm/__init__.py
auxi/mpp/gas/Vm/_clapeyron_binary.py
auxi/mpp/gas/Vm/_clapeyron_binary.yaml
auxi/mpp/gas/Vm/_clapeyron_multi.py
auxi/mpp/gas/Vm/_clapeyron_multi.yaml
auxi/mpp/gas/Vm/_clapeyron_unary.py
auxi/mpp/gas/Vm/_clapeyron_unary.yaml
auxi/mpp/gas/Vm/_model.py
auxi/mpp/gas/state/__init__.py
auxi/mpp/gas/state/_gas_binary_tpx_pl_state.py
auxi/mpp/gas/state/_gas_binary_tpx_state.py
auxi/mpp/gas/state/_gas_tpx_pl_state.py
auxi/mpp/gas/state/_gas_tpx_state.py
auxi/mpp/gas/state/_gas_unary_tpx_pl_state.py
auxi/mpp/gas/state/_gas_unary_tpx_state.py
auxi/mpp/gas/ɛ/__init__.py
auxi/mpp/gas/ɛ/_edwards_felske_tien_unary.py
auxi/mpp/gas/ɛ/_edwards_felske_tien_unary.yaml
auxi/mpp/gas/ɛ/_edwards_leckner_binary.py
auxi/mpp/gas/ɛ/_edwards_leckner_multi.py
auxi/mpp/gas/ɛ/_edwards_leckner_unary.py
auxi/mpp/gas/ɛ/_leckner_binary.py
auxi/mpp/gas/ɛ/_leckner_unary.py
auxi/mpp/gas/ɛ/_leckner_unary.yaml
auxi/mpp/gas/ɛ/_model.py
auxi/mpp/gas/κ/__init__.py
auxi/mpp/gas/κ/_assael_unary.py
auxi_mpp-2.7.0.dist-info/licenses/LICENSE.md
auxi_mpp-2.7.0.dist-info/METADATA
auxi_mpp-2.7.0.dist-info/WHEEL
auxi_mpp-2.7.0.dist-info/top_level.txt
auxi_mpp-2.7.0.dist-info/RECORD
