Metadata-Version: 2.4
Name: auxi-mpp
Version: 2.7.0
Summary: `auxi` provides tools to help users do calculations for metallurgical process engineering. `auxi-mpp` provides tools for calculating material physical properties.
Author-email: Johan Zietsman <johan.zietsman@ex-mente.co.za>, Hanno Muire <hanno.muire@ex-mente.co.za>, Stefan Koning <stefan.koning@ex-mente.co.za>
Maintainer-email: Stefan van der Merwe <stefan.vandermerwe@ex-mente.co.za>, Thys Nortje <thys.nortje@ex-mente.co.za>
Classifier: Development Status :: 5 - Production/Stable
Classifier: Programming Language :: Python :: 3
Classifier: Operating System :: POSIX :: Linux
Classifier: Environment :: Console
Requires-Python: >=3.12
License-File: LICENSE.md
Requires-Dist: auxi-chemistry>=2.7.0
Requires-Dist: polars>=1.21.0
Requires-Dist: pytest>=8.3.5
Requires-Dist: pyyaml>=6.0.2
Requires-Dist: scipy>=1.16.1
Requires-Dist: sphinx-design>=0.6.1
Requires-Dist: sphinx-tabs>=3.4.7
Dynamic: license-file
